pollination_streamlit_io/__init__.py
pollination_streamlit_io/components_callbacks.py
pollination_streamlit_io/utils.py
pollination_streamlit_io/components/frontend/package-lock.json
pollination_streamlit_io/components/frontend/build/asset-manifest.json
pollination_streamlit_io/components/frontend/build/bootstrap.min.css
pollination_streamlit_io/components/frontend/build/index.html
pollination_streamlit_io/components/frontend/build/static/js/main.9cd611e6.js
pollination_streamlit_io/components/frontend/build/static/js/main.9cd611e6.js.LICENSE.txt
pollination_streamlit_io/components/frontend/build/static/js/main.9cd611e6.js.map
pollination_streamlit_io-0.84.4.dist-info/LICENSE
pollination_streamlit_io-0.84.4.dist-info/METADATA
pollination_streamlit_io-0.84.4.dist-info/WHEEL
pollination_streamlit_io-0.84.4.dist-info/top_level.txt
pollination_streamlit_io-0.84.4.dist-info/RECORD
