Metadata-Version: 2.1
Name: pollination-streamlit-io
Version: 0.84.4
Summary: Pollination input/output components for Streamlit
Home-page: https://github.com/pollination/pollination-streamlit-io
Author: Ladybug Tools
Author-email: info@ladybug.tools
License: Apache-2.0 License
Platform: UNKNOWN
Requires-Python: >=3.7
License-File: LICENSE
Requires-Dist: streamlit (>=1.11.1)
Requires-Dist: pollination-streamlit (>=0.8.3)
